{
  "timestamp": "2025-08-04T23:20:32.563194",
  "analysis": {
    "score": 3.25,
    "summary": "****  \n\n**Nome Completo:** Bruno Pereira Estevão  \n\n**Experiência Relevante:**  \n• Operador de Caixa na Assai Atacadista (2021–2024)  \n• Central de Atendimento ao Cliente na Assai Atacadista (2024–2025)  \n\n**Habilidades Técnicas:**  \n• Pacote Office intermediário  \n• Atendimento ao cliente  \n• Emissão de notas fiscais/recibos  \n\n**Formação Acadêmica:**  \n• Ensino Médio Completo (EREM Maria Auxiliadora Liberato)  \n• Informática Básica (SENAC)  \n• Educação Física (Anhanguera) – Cursando  \n\n**Idiomas:** Não informado  \n\n**Informações de Contato:**  \n• Email: brunopereira007123@gmail.com  \n• Telefone: 81-991688079  \n\n  \n\n**",
    "analysis": "**  \n\n**1. ALINHAMENTO TÉCNICO:**  \n• **Experiência relevante:** Operador de Caixa e Central de Atendimento ao Cliente na Assai Atacadista (2021–2025).  \n• **Competências alinhadas:**  \n  - Emissão de notas fiscais/recibos (parcialmente alinhado com a emissão de NFS-e).  \n  - Atendimento ao cliente (habilidade transferível para comunicação interna/externa).  \n  - Conhecimento intermediário do Pacote Office (pode auxiliar em tarefas básicas de dados).  \n• **Adequação à vaga:** O candidato tem experiência limitada em funções administrativas e financeiras, mas nenhuma experiência específica com provisionamento de impostos, integração de lotes contábeis ou ERP.  \n\n**2. GAPS IDENTIFICADOS:**  \n• **Lacunas técnicas:**  \n  - Nenhuma experiência com ERP, retenção de impostos (PIS, COFINS, IRRF, etc.), ou conciliação contábil.  \n  - Não menciona conhecimentos em legislação tributária ou processos fiscais.  \n• **Conhecimentos em falta:**  \n  - Domínio de sistemas contábeis/fiscais.  \n  - Cálculo e emissão de guias de impostos.  \n• **Áreas de desenvolvimento:**  \n  - Curso técnico em contabilidade ou tributação.  \n  - Treinamento em ERPs (ex.: SAP, Totvs).  \n\n**3. RECOMENDAÇÃO FINAL: INADEQUADO**  \n• **Pontos fortes:**  \n  - Experiência em emissão de documentos fiscais básicos.  \n  - Organização e atendimento ao cliente.  \n• **Limitações:**  \n  - Falta de experiência comprovada em funções contábeis/fiscais.  \n  - Sem conhecimentos técnicos exigidos para a vaga (ERP, impostos, conciliação).  \n• **Justificativa:** O perfil não atende aos requisitos técnicos da vaga, que exige experiência específica em processos fiscais, contábeis e sistemas ERP. Recomendado para vagas administrativas básicas ou de atendimento.",
    "skills": [],
    "experience_years": 1,
    "education_level": "Não informado",
    "match_reasons": [
      "Score: 3.25/10"
    ],
    "recommendations": [
      "Avaliação baseada em experiência e habilidades técnicas"
    ]
  },
  "job_id": 2,
  "cache_key": "24c4b8da8d81f604847be4d122ae70e3"
}