{
  "timestamp": "2025-08-04T23:25:05.580314",
  "analysis": {
    "score": 3.5,
    "summary": "****  \n\n**Nome Completo:** Julia Anna Gomes  \n\n**Experiência Relevante:**  \n• Aprendiz Administrativo na CELPE - NEOENERGIA (2018 - 2019)  \n\n**Habilidades Técnicas:**  \n• Escuta ativa e Comunicação  \n• Trabalho em equipe  \n• Atenção aos detalhes  \n• Planejamento e execução de tarefas  \n\n**Formação Acadêmica:**  \n• Bacharelado em Fisioterapia (2020 - 2024) - ASCES - UNITA  \n• Ensino Médio (2015 - 2017) - Colégio Adventista de Caruaru  \n\n**Idiomas:**  \n• Português: Nativo  \n• Inglês: Intermediário  \n\n**Informações de Contato:**  \n• Email: juliaannacarvalho@gmail.com  \n• Telefone: (81) 99238-5663  \n\n  \n\n**",
    "analysis": "**  \n\n**1. ALINHAMENTO TÉCNICO:**  \n• **Experiência relevante:** Aprendiz Administrativo na CELPE - NEOENERGIA (2018 - 2019)  \n• **Competências alinhadas:** Atenção aos detalhes, Planejamento e execução de tarefas, Trabalho em equipe  \n• **Adequação à vaga:** O currículo demonstra habilidades administrativas básicas e capacidade de organização, mas não apresenta experiência específica com processos contábeis, impostos ou sistemas ERP, que são essenciais para a vaga.  \n\n**2. GAPS IDENTIFICADOS:**  \n• **Lacunas técnicas:** Falta de experiência com provisionamento de impostos, emissão de NFS-e, conciliação contábil e uso de ERPs.  \n• **Conhecimentos em falta:** Legislação tributária, processos fiscais e contábeis, ferramentas de gestão financeira.  \n• **Áreas de desenvolvimento:** Cursos técnicos em contabilidade/tributação e experiência prática com sistemas de faturamento e impostos.  \n\n**3. RECOMENDAÇÃO FINAL:** **INADEQUADO**  \n• **Pontos fortes:** Organização, trabalho em equipe e atenção a detalhes.  \n• **Limitações:** Ausência de experiência comprovada em atividades fiscais, contábeis ou de gestão de impostos.  \n• **Justificativa:** O perfil não atende aos requisitos técnicos da vaga, que exige conhecimentos específicos em tributação, conciliação contábil e operação de sistemas ERP. A experiência administrativa é insuficiente para as responsabilidades descritas.  \n\n  \n**Observação:** A análise foi estritamente baseada nas informações fornecidas no currículo. Dados não mencionados (ex.: certificações em contabilidade, experiência com impostos) foram considerados como \"Não informados\".",
    "skills": [
      "Git",
      "Api"
    ],
    "experience_years": 1,
    "education_level": "Não informado",
    "match_reasons": [
      "Score: 3.5/10"
    ],
    "recommendations": [
      "Avaliação baseada em experiência e habilidades técnicas"
    ]
  },
  "job_id": 2,
  "cache_key": "371d126423f49317c04c2350cef9e3b1"
}